gmcp/__init__.py
gmcp/server.py
gmcp-0.2.2.dist-info/METADATA
gmcp-0.2.2.dist-info/WHEEL
gmcp-0.2.2.dist-info/entry_points.txt
gmcp-0.2.2.dist-info/RECORD
