Metadata-Version: 2.4
Name: gmcp
Version: 0.2.2
Summary: Transform any FastAPI server into an MCP server
Project-URL: Homepage, https://github.com/gaurav98095/gmcp
Project-URL: Repository, https://github.com/gaurav98095/gmcp
Author-email: Your Name <your@email.com>
License: MIT
Keywords: agent,api,fastapi,mcp,server
Classifier: License :: OSI Approved :: MIT License
Classifier: Operating System :: OS Independent
Classifier: Programming Language :: Python :: 3
Classifier: Programming Language :: Python :: 3.10
Requires-Python: >=3.10
Requires-Dist: httpx>=0.27.0
Requires-Dist: mcp>=1.0.0
Requires-Dist: pydantic>=2.0.0
